Metadata-Version: 1.1
Name: grg-mpdata
Version: 0.1.1
Summary: Data structures and methods for reading and writing Matpower data files
Home-page: https://github.com/lanl-ansi/grg-mpdata
Author: Carleton Coffrin
Author-email: cjc@lanl.gov
License: BSD
Platform: UNKNOWN
Classifier: Development Status :: 4 - Beta
Classifier: Intended Audience :: Developers
Classifier: License :: OSI Approved :: BSD License
Classifier: Operating System :: OS Independent
Classifier: Programming Language :: Python
Classifier: Programming Language :: Python :: 3
Classifier: Programming Language :: Python :: 3.5
Classifier: Programming Language :: Python :: 3.6
Classifier: Programming Language :: Python :: 3.7
